rjgtoys_config-0.0.2-py3.8-nspkg.pth
rjgtoys/config/__init__.py
rjgtoys/config/_config.py
rjgtoys/config/_manager.py
rjgtoys/config/_ops.py
rjgtoys/config/_proxy.py
rjgtoys/config/_source.py
rjgtoys_config-0.0.2.dist-info/METADATA
rjgtoys_config-0.0.2.dist-info/WHEEL
rjgtoys_config-0.0.2.dist-info/namespace_packages.txt
rjgtoys_config-0.0.2.dist-info/top_level.txt
rjgtoys_config-0.0.2.dist-info/RECORD
