Metadata-Version: 2.1
Name: rjgtoys-config
Version: 0.0.2
Summary: A modular interface for configuration data
Home-page: UNKNOWN
Author: Bob Gautier
Author-email: bob.gautier@gmail.com
License: GPL
Keywords: configuration
Platform: UNKNOWN
Classifier: Development Status :: 2 - Pre-Alpha
Classifier: License :: OSI Approved :: GNU General Public License v2 or later (GPLv2+)
Requires-Dist: pydantic
Requires-Dist: rjgtoys-xc
Requires-Dist: rjgtoys-thing
Requires-Dist: rjgtoys-yaml
